MANIFEST.in
setup.py
mtspec/VERSION.txt
mtspec/__init__.py
mtspec/multitaper.py
mtspec/util.py
mtspec.egg-info/PKG-INFO
mtspec.egg-info/SOURCES.txt
mtspec.egg-info/dependency_links.txt
mtspec.egg-info/not-zip-safe
mtspec.egg-info/pbr.json
mtspec.egg-info/requires.txt
mtspec.egg-info/top_level.txt
mtspec/src/src/.DS_Store
mtspec/src/src/.mtspec.f90.swp
mtspec/src/src/adaptspec.f90
mtspec/src/src/atanh2.f90
mtspec/src/src/df_spec.f90
mtspec/src/src/dpss.f90
mtspec/src/src/dpss_ev.f90
mtspec/src/src/dpss_spline.f90
mtspec/src/src/eigenft.f90
mtspec/src/src/fdis.f90
mtspec/src/src/fft.f90
mtspec/src/src/ftest.f90
mtspec/src/src/ifft.f90
mtspec/src/src/jackspec.f90
mtspec/src/src/mt_cohe.f90
mtspec/src/src/mt_deconv.f90
mtspec/src/src/mt_transfer.f90
mtspec/src/src/mtspec.f90
mtspec/src/src/nearn.f90
mtspec/src/src/nnls.f90
mtspec/src/src/nsinv.f90
mtspec/src/src/nsqi.f90
mtspec/src/src/oct_spec.f90
mtspec/src/src/psd_reshape.f90
mtspec/src/src/pythag.f90
mtspec/src/src/qiinv.f90
mtspec/src/src/qrfac.f90
mtspec/src/src/qsnorm.f90
mtspec/src/src/qtdis.f90
mtspec/src/src/rsm_eig.f90
mtspec/src/src/set_xint.f90
mtspec/src/src/sft.f90
mtspec/src/src/sine_cohe.f90
mtspec/src/src/sine_psd.f90
mtspec/src/src/spectra.f90
mtspec/src/src/spline.f90
mtspec/src/src/sym_fft.f90
mtspec/src/src/tinvit.f90
mtspec/src/src/trbak1.f90
mtspec/src/src/tred1.f90
mtspec/src/src/tridib.f90
mtspec/src/src/wv_spec.f90
mtspec/src/src/wv_spec_to_array.f90
mtspec/src/src/xint.f90
mtspec/src/src/yule.f90
mtspec/src/src/zqrfac.f90
mtspec/tests/__init__.py
mtspec/tests/__main__.py
mtspec/tests/test_code_formatting.py
mtspec/tests/test_multitaper.py
mtspec/tests/data/ADO.dat.gz
mtspec/tests/data/PASC.dat.gz
mtspec/tests/data/dpss.npz
mtspec/tests/data/fstatistics.npz
mtspec/tests/data/mt_cohe.npz
mtspec/tests/data/mtspec_pad_with_errors.npz
mtspec/tests/data/multitaper.npz
mtspec/tests/data/noise_deconv_first_1000_numbers.dat.gz
mtspec/tests/data/quadratic_multitaper.npz
mtspec/tests/data/sine_psd.npz
mtspec/tests/data/single_taper.npz
mtspec/tests/data/v22_174_series.dat.gz
mtspec/tests/data/wv.npz