Metadata-Version: 1.1
Name: mtspec
Version: 0.3.2
Summary: Python bindings for multitaper `mtspec` f90 Library.
Home-page: https://github.com/krischer/mtspec
Author:  Lion Krischer, Moritz Beyreuther, and German A. Prieto
Author-email: krischer@geophysik.uni-muenchen.de
License: GNU General Public License, version 3 (GPLv3)
Keywords: mtspec,multitaper,seismology,waveform,signal,processing,taper,wigner,ville,multitaper,seismology,signal processing
Platform: OS Independent
Classifier: Development Status :: 4 - Beta
Classifier: Environment :: Console
Classifier: Intended Audience :: Science/Research
Classifier: Intended Audience :: Developers
Classifier: Operating System :: Unix
Classifier: Operating System :: POSIX
Classifier: Operating System :: MacOS
Classifier: License :: OSI Approved :: GNU General Public License v3 (GPLv3)
Classifier: Programming Language :: Python
Classifier: Programming Language :: Python :: 2
Classifier: Programming Language :: Python :: 2.7
Classifier: Programming Language :: Python :: 3
Classifier: Programming Language :: Python :: 3.3
Classifier: Programming Language :: Python :: 3.4
Classifier: Programming Language :: Python :: 3.5
Classifier: Programming Language :: Python :: Implementation :: CPython
Classifier: Topic :: Scientific/Engineering
Classifier: Topic :: Scientific/Engineering :: Physics
